[
    {
        "repo_name": "airflow",
        "repo_url": "apache/airflow",
        "issue_html_url": "https://github.com/apache/airflow/issues/14202",
        "earliest_issue_date": "2021-02-12T06:56:10Z",
        "fix_commit_hash": "e164080479775aca53146331abf6f615d1f03ff0",
        "tipo": "PR",
        "matched": [
            "d93555b863a03754b1bf1d3a3362108be275de9e"
        ]
    },
    {
        "repo_name": "airflow",
        "repo_url": "apache/airflow",
        "issue_html_url": "https://github.com/apache/airflow/issues/14200",
        "earliest_issue_date": "2021-02-11T19:31:08Z",
        "fix_commit_hash": "2c1880a90712aa79dd7c16c78a93b343cd312268",
        "tipo": "PR",
        "matched": [
            "9d4b914fa29982514cdac3d6458dcd6f827dda0a"
        ]
    },
    {
        "repo_name": "airflow",
        "repo_url": "apache/airflow",
        "issue_html_url": "https://github.com/apache/airflow/issues/14182",
        "earliest_issue_date": "2021-02-10T21:36:28Z",
        "fix_commit_hash": "e0ee91e15f8385e34e3d7dfc8a6365e350ea7083",
        "tipo": "PR",
        "matched": [
            "c0920efc012468681cff3d3c9cfe25c7381dc976"
        ]
    },
    {
        "repo_name": "airflow",
        "repo_url": "apache/airflow",
        "issue_html_url": "https://github.com/apache/airflow/issues/14178",
        "earliest_issue_date": "2021-02-10T17:56:57Z",
        "fix_commit_hash": "0891a8ea73813d878c0d00fbfdb59fa360e8d1cf",
        "tipo": "PR",
        "matched": [
            "66e738296a81a80e56457981c3ac93f835200c30"
        ]
    },
    {
        "repo_name": "airflow",
        "repo_url": "apache/airflow",
        "issue_html_url": "https://github.com/apache/airflow/issues/14168",
        "earliest_issue_date": "2021-02-10T09:19:07Z",
        "fix_commit_hash": "c747bce135c5bcbc92645c226cb90fd99dc62be5",
        "tipo": "PR",
        "matched": []
    },
    {
        "repo_name": "airflow",
        "repo_url": "apache/airflow",
        "issue_html_url": "https://github.com/apache/airflow/issues/14163",
        "earliest_issue_date": "2021-02-10T04:13:18Z",
        "fix_commit_hash": "4ee442970873ba59ee1d1de3ac78ef8e33666e0f",
        "tipo": "PR",
        "matched": [
            "59dad1a4ea6f3ba39d7be8c46ee45ea7cb0dd1f9"
        ]
    },
    {
        "repo_name": "airflow",
        "repo_url": "apache/airflow",
        "issue_html_url": "https://github.com/apache/airflow/issues/14154",
        "earliest_issue_date": "2021-02-09T19:18:39Z",
        "fix_commit_hash": "d612495502cfc521c4a80f1e84ad61c740f6e07e",
        "tipo": "PR",
        "matched": [
            "49c193fb872856500d8919facf45b9ab5207a093"
        ]
    },
    {
        "repo_name": "airflow",
        "repo_url": "apache/airflow",
        "issue_html_url": "https://github.com/apache/airflow/issues/14106",
        "earliest_issue_date": "2021-02-05T16:47:46Z",
        "fix_commit_hash": "af2d11e36ed43b0103a54780640493b8ae46d70e",
        "tipo": "PR",
        "matched": [
            "1ef56df74a219d8bdda33a508e914d13de2fd0bc"
        ]
    },
    {
        "repo_name": "airflow",
        "repo_url": "apache/airflow",
        "issue_html_url": "https://github.com/apache/airflow/issues/14104",
        "earliest_issue_date": "2021-02-05T15:31:07Z",
        "fix_commit_hash": "af5eb55943821cabe68c63f9e3287f828eede06c",
        "tipo": "PR",
        "matched": [
            "bc026cf6961626dd01edfaf064562bfb1f2baf42"
        ]
    },
    {
        "repo_name": "airflow",
        "repo_url": "apache/airflow",
        "issue_html_url": "https://github.com/apache/airflow/issues/14097",
        "earliest_issue_date": "2021-02-05T12:13:09Z",
        "fix_commit_hash": "e3bcaa3ba351234effe52ad380345c4e39003fcb",
        "tipo": "PR",
        "matched": [
            "28261f118000aefbedee0a6a0385a4fcf8ef37a5"
        ]
    }
]