[
    {
        "repo_name": "airflow",
        "repo_url": "apache/airflow",
        "issue_html_url": "https://github.com/apache/airflow/issues/31795",
        "earliest_issue_date": "2023-06-08T14:24:33Z",
        "fix_commit_hash": "1b599c9fbfb6151a41a588edaa786745f50eec38",
        "tipo": "PR",
        "matched": []
    },
    {
        "repo_name": "airflow",
        "repo_url": "apache/airflow",
        "issue_html_url": "https://github.com/apache/airflow/issues/31769",
        "earliest_issue_date": "2023-06-07T15:08:32Z",
        "fix_commit_hash": "bd32467ede1a5a197e09456803f7cebaee9f9b77",
        "tipo": "PR",
        "matched": [
            "aefa482051ec249f42095286a0fe4cf0eec1f6f4"
        ]
    },
    {
        "repo_name": "airflow",
        "repo_url": "apache/airflow",
        "issue_html_url": "https://github.com/apache/airflow/issues/31761",
        "earliest_issue_date": "2023-06-07T11:47:11Z",
        "fix_commit_hash": "b9efbf513d8390b66d01ee380ccc43cd60d3c88b",
        "tipo": "PR",
        "matched": [
            "a80707fdd2a5fcfbe5c336871128fdf39b7d575f"
        ]
    },
    {
        "repo_name": "airflow",
        "repo_url": "apache/airflow",
        "issue_html_url": "https://github.com/apache/airflow/issues/31753",
        "earliest_issue_date": "2023-06-07T06:44:13Z",
        "fix_commit_hash": "049c6184b730a7ede41db9406654f054ddc8cc5f",
        "tipo": "PR",
        "matched": [
            "db5375bea7a0564c12f56c91e1c8c7b6c049698c"
        ]
    },
    {
        "repo_name": "airflow",
        "repo_url": "apache/airflow",
        "issue_html_url": "https://github.com/apache/airflow/issues/31750",
        "earliest_issue_date": "2023-06-07T03:06:11Z",
        "fix_commit_hash": "b502e665d633262f3ce52d9c002c0a25e6e4ec9d",
        "tipo": "PR",
        "matched": [
            "86768859c689bf02ced96e71996a3a30da1b5888"
        ]
    },
    {
        "repo_name": "airflow",
        "repo_url": "apache/airflow",
        "issue_html_url": "https://github.com/apache/airflow/issues/31745",
        "earliest_issue_date": "2023-06-06T18:40:42Z",
        "fix_commit_hash": "b5057e0e1fc6b7a47e38037a97cac862706747f0",
        "tipo": "PR",
        "matched": [
            "971039454a3684d0ea7261dfe91f34ac4b62af72"
        ]
    },
    {
        "repo_name": "airflow",
        "repo_url": "apache/airflow",
        "issue_html_url": "https://github.com/apache/airflow/issues/31738",
        "earliest_issue_date": "2023-06-06T10:07:18Z",
        "fix_commit_hash": "f05beb721940c36f2c501ea8657516262b99c01e",
        "tipo": "PR",
        "matched": [
            "0a68588479e34cf175d744ea77b283d9d78ea71a"
        ]
    },
    {
        "repo_name": "airflow",
        "repo_url": "apache/airflow",
        "issue_html_url": "https://github.com/apache/airflow/issues/31726",
        "earliest_issue_date": "2023-06-06T02:39:47Z",
        "fix_commit_hash": "fe4a6c843acd97c776d5890116bfa85356a54eee",
        "tipo": "PR",
        "matched": [
            "2c2b827f3aa863eab80b6dd7ebeb68149cada814"
        ]
    },
    {
        "repo_name": "airflow",
        "repo_url": "apache/airflow",
        "issue_html_url": "https://github.com/apache/airflow/issues/31720",
        "earliest_issue_date": "2023-06-05T18:55:20Z",
        "fix_commit_hash": "a60429eadfffb5fb0f867c220a6cecf628692dcf",
        "tipo": "PR",
        "matched": [
            "16b8c476518ed76e3689966ec4b0b788be935410"
        ]
    },
    {
        "repo_name": "airflow",
        "repo_url": "apache/airflow",
        "issue_html_url": "https://github.com/apache/airflow/issues/31675",
        "earliest_issue_date": "2023-06-02T05:40:57Z",
        "fix_commit_hash": "e01ff4749cb2469b21f467a1b0089d0115f39368",
        "tipo": "PR",
        "matched": [
            "f02a7e9a8292909b369daae6d573f58deed04440"
        ]
    }
]