[{"repo_name": "airflow", "repo_url": "apache/airflow", "issue_html_url": "https://github.com/apache/airflow/issues/22829", "earliest_issue_date": "2022-04-07T13:58:27Z", "fix_commit_hash": "8b6b0848a3cacf9999477d6af4d2a87463f03026", "tipo": "PR", "inducing_commit_hash_pyszz": ["5247445ff13e4b9cf73c26f902af03791f48f04d"]}, {"repo_name": "airflow", "repo_url": "apache/airflow", "issue_html_url": "https://github.com/apache/airflow/issues/22828", "earliest_issue_date": "2022-04-07T13:56:57Z", "fix_commit_hash": "8b6b0848a3cacf9999477d6af4d2a87463f03026", "tipo": "PR", "inducing_commit_hash_pyszz": ["5247445ff13e4b9cf73c26f902af03791f48f04d"]}, {"repo_name": "airflow", "repo_url": "apache/airflow", "issue_html_url": "https://github.com/apache/airflow/issues/22827", "earliest_issue_date": "2022-04-07T13:55:50Z", "fix_commit_hash": "10078287e2bc5df0cf4f1889fdd6714c6a766b9e", "tipo": "PR", "inducing_commit_hash_pyszz": ["4fb929a60966e9cecbbb435efd375adcc4fff9d7"]}, {"repo_name": "airflow", "repo_url": "apache/airflow", "issue_html_url": "https://github.com/apache/airflow/issues/22826", "earliest_issue_date": "2022-04-07T13:55:11Z", "fix_commit_hash": "8b6b0848a3cacf9999477d6af4d2a87463f03026", "tipo": "PR", "inducing_commit_hash_pyszz": ["5247445ff13e4b9cf73c26f902af03791f48f04d"]}, {"repo_name": "airflow", "repo_url": "apache/airflow", "issue_html_url": "https://github.com/apache/airflow/issues/22825", "earliest_issue_date": "2022-04-07T13:54:00Z", "fix_commit_hash": "8b6b0848a3cacf9999477d6af4d2a87463f03026", "tipo": "PR", "inducing_commit_hash_pyszz": ["5247445ff13e4b9cf73c26f902af03791f48f04d"]}, {"repo_name": "airflow", "repo_url": "apache/airflow", "issue_html_url": "https://github.com/apache/airflow/issues/22821", "earliest_issue_date": "2022-04-07T13:49:32Z", "fix_commit_hash": "7c64b921f2dca57598740bd308bab1d1fdf35d84", "tipo": "PR", "inducing_commit_hash_pyszz": ["5247445ff13e4b9cf73c26f902af03791f48f04d"]}, {"repo_name": "airflow", "repo_url": "apache/airflow", "issue_html_url": "https://github.com/apache/airflow/issues/22810", "earliest_issue_date": "2022-04-07T10:43:06Z", "fix_commit_hash": "bf10545d8358bcdb9ca5dacba101482296251cab", "tipo": "PR", "inducing_commit_hash_pyszz": ["4a21b62161a8e14f0dbc06f292f4662832c52669"]}, {"repo_name": "airflow", "repo_url": "apache/airflow", "issue_html_url": "https://github.com/apache/airflow/issues/22782", "earliest_issue_date": "2022-04-06T14:29:05Z", "fix_commit_hash": "7331eefc393b8f1fae6f3cf061cf17eb5eaa3fc8", "tipo": "PR", "inducing_commit_hash_pyszz": []}, {"repo_name": "airflow", "repo_url": "apache/airflow", "issue_html_url": "https://github.com/apache/airflow/issues/22762", "earliest_issue_date": "2022-04-05T19:07:27Z", "fix_commit_hash": "26a96fa76a41a6abc9f276e8ac32f21bde6ff022", "tipo": "PR", "inducing_commit_hash_pyszz": ["8fdcc5760a104b0e4e5558191e0269bf873f8768"]}, {"repo_name": "airflow", "repo_url": "apache/airflow", "issue_html_url": "https://github.com/apache/airflow/issues/22738", "earliest_issue_date": "2022-04-04T20:47:44Z", "fix_commit_hash": "ce8ea6691820140a0e2d9a5dad5254bc05a5a270", "tipo": "PR", "inducing_commit_hash_pyszz": ["deb953d9b3c1cf450aee9dfe92f81e9ffa768f06"]}]