[
    {
        "fix_commit_hash": "e60be9e3d41a64856529e594ba6c1db680650377",
        "repo_name": "airflow",
        "best_scenario_issue_date": "2023-03-10T15:08:06+03:00"
    },
    {
        "fix_commit_hash": "25e173abb1dc2bcf04a56e06a130cfe421b68568",
        "repo_name": "airflow",
        "best_scenario_issue_date": "2024-12-01T15:20:44+01:00"
    },
    {
        "fix_commit_hash": "21151fb7eaddb9d3be647e2e6f10303ab821528e",
        "repo_name": "airflow",
        "best_scenario_issue_date": "2022-02-24T22:08:02+08:00"
    },
    {
        "fix_commit_hash": "e0f4de347fd22538b1fdc5cd303fd7ec55d970ab",
        "repo_name": "airflow",
        "best_scenario_issue_date": "2023-06-26T22:49:05-07:00"
    },
    {
        "fix_commit_hash": "b87cbc388bae281e553da699212ebfc6bb723eea",
        "repo_name": "airflow",
        "best_scenario_issue_date": "2023-03-15T21:45:37+01:00"
    },
    {
        "fix_commit_hash": "127f8f4de02422ade8f2c84f84d3262d6efde185",
        "repo_name": "airflow",
        "best_scenario_issue_date": "2022-06-16T14:36:32-04:00"
    },
    {
        "fix_commit_hash": "bb26f96665567325a7fbb810249820e7dac0322a",
        "repo_name": "airflow",
        "best_scenario_issue_date": "2022-02-28T20:26:47-05:00"
    },
    {
        "fix_commit_hash": "d7bd6d780aa3db825e6baae7fc1a7d8ae0f8b14b",
        "repo_name": "airflow",
        "best_scenario_issue_date": "2022-12-23T12:25:55+01:00"
    },
    {
        "fix_commit_hash": "dba3e4ec51c03dc08449a3954fa3539388d0bc73",
        "repo_name": "airflow",
        "best_scenario_issue_date": "2022-06-15T10:23:49-06:00"
    },
    {
        "fix_commit_hash": "b1fdcdfe6778574c53bdf6bcbd59090c59605287",
        "repo_name": "airflow",
        "best_scenario_issue_date": "2022-03-09T19:02:00+08:00"
    }
]