[
    {
        "repo_name": "junit5",
        "repo_url": "junit-team/junit5",
        "issue_html_url": "https://github.com/junit-team/junit5/issues/1845",
        "earliest_issue_date": "2019-04-04T15:07:55Z",
        "fix_commit_hash": "06eeceb0978dd1059f7dd9ffd15c7552d7ad7553",
        "tipo": "Commit"
    },
    {
        "repo_name": "junit5",
        "repo_url": "junit-team/junit5",
        "issue_html_url": "https://github.com/junit-team/junit5/issues/1836",
        "earliest_issue_date": "2019-03-27T08:23:22Z",
        "fix_commit_hash": "18f8905e897ee267b5c27e719df7d3f079bc698a",
        "tipo": "PR"
    },
    {
        "repo_name": "junit5",
        "repo_url": "junit-team/junit5",
        "issue_html_url": "https://github.com/junit-team/junit5/issues/1805",
        "earliest_issue_date": "2019-03-09T19:14:47Z",
        "fix_commit_hash": "732c38c564586a6cfef45b01f3a475523aa7f118",
        "tipo": "Commit"
    },
    {
        "repo_name": "junit5",
        "repo_url": "junit-team/junit5",
        "issue_html_url": "https://github.com/junit-team/junit5/issues/1801",
        "earliest_issue_date": "2019-03-06T13:56:18Z",
        "fix_commit_hash": "835160321973c08ba03cd5792d6e42b2866aa98f",
        "tipo": "Commit"
    },
    {
        "repo_name": "junit5",
        "repo_url": "junit-team/junit5",
        "issue_html_url": "https://github.com/junit-team/junit5/issues/1800",
        "earliest_issue_date": "2019-03-05T13:26:06Z",
        "fix_commit_hash": "30ab9f4fa8dcf05b44343faa6836c46e0c2d88be",
        "tipo": "Commit"
    },
    {
        "repo_name": "junit5",
        "repo_url": "junit-team/junit5",
        "issue_html_url": "https://github.com/junit-team/junit5/issues/1797",
        "earliest_issue_date": "2019-02-27T16:31:10Z",
        "fix_commit_hash": "c4bc11a662506ae9d1633552155e8ffa02e3c930",
        "tipo": "Commit"
    },
    {
        "repo_name": "junit5",
        "repo_url": "junit-team/junit5",
        "issue_html_url": "https://github.com/junit-team/junit5/issues/1793",
        "earliest_issue_date": "2019-02-24T08:32:25Z",
        "fix_commit_hash": "a8c7c0f307ff98ca41deccb7b1f50f8b6d9f97b4",
        "tipo": "PR"
    },
    {
        "repo_name": "junit5",
        "repo_url": "junit-team/junit5",
        "issue_html_url": "https://github.com/junit-team/junit5/issues/1788",
        "earliest_issue_date": "2019-02-19T09:29:15Z",
        "fix_commit_hash": "ac0f6dc379c30a3c821dfbffc73f95732734b6b1",
        "tipo": "PR"
    },
    {
        "repo_name": "junit5",
        "repo_url": "junit-team/junit5",
        "issue_html_url": "https://github.com/junit-team/junit5/issues/1787",
        "earliest_issue_date": "2019-02-18T15:02:57Z",
        "fix_commit_hash": "c4e0a26deb6194c0221410d9fa8261cf3ffd3719",
        "tipo": "PR"
    },
    {
        "repo_name": "junit5",
        "repo_url": "junit-team/junit5",
        "issue_html_url": "https://github.com/junit-team/junit5/issues/1781",
        "earliest_issue_date": "2019-02-16T13:50:11Z",
        "fix_commit_hash": "4f4dd3177625e88dc31e55d19eb1ef37750dee43",
        "tipo": "Commit"
    }
]